odoo/addons/mis_builder_operating_unit/README.rst
odoo/addons/mis_builder_operating_unit/__init__.py
odoo/addons/mis_builder_operating_unit/__manifest__.py
odoo/addons/mis_builder_operating_unit/i18n/da.po
odoo/addons/mis_builder_operating_unit/i18n/mis_builder_operating_unit.pot
odoo/addons/mis_builder_operating_unit/model/__init__.py
odoo/addons/mis_builder_operating_unit/model/mis_builder.py
odoo/addons/mis_builder_operating_unit/readme/CONTRIBUTORS.rst
odoo/addons/mis_builder_operating_unit/readme/DESCRIPTION.rst
odoo/addons/mis_builder_operating_unit/readme/USAGE.rst
odoo/addons/mis_builder_operating_unit/security/mis_builder_security.xml
odoo/addons/mis_builder_operating_unit/static/description/icon.png
odoo/addons/mis_builder_operating_unit/static/description/index.html
odoo/addons/mis_builder_operating_unit/tests/__init__.py
odoo/addons/mis_builder_operating_unit/tests/test_mis_builder_operating_unit.py
odoo/addons/mis_builder_operating_unit/view/mis_builder.xml
odoo13_addon_mis_builder_operating_unit-13.0.1.1.0.dist-info/METADATA
odoo13_addon_mis_builder_operating_unit-13.0.1.1.0.dist-info/WHEEL
odoo13_addon_mis_builder_operating_unit-13.0.1.1.0.dist-info/top_level.txt
odoo13_addon_mis_builder_operating_unit-13.0.1.1.0.dist-info/RECORD
